fiberphotopy/__init__.py
fiberphotopy/plotting/__init__.py
fiberphotopy/plotting/fp_viz.py
fiberphotopy/plotting/fp_viz_utils.py
fiberphotopy/preprocess/__init__.py
fiberphotopy/preprocess/expt_config.py
fiberphotopy/preprocess/fp_data.py
fiberphotopy/preprocess/tfc_data.py
fiberphotopy/stats/psth_stats.py
fiberphotopy-0.2.31.dist-info/LICENSE.txt
fiberphotopy-0.2.31.dist-info/WHEEL
fiberphotopy-0.2.31.dist-info/METADATA
fiberphotopy-0.2.31.dist-info/RECORD
