Metadata-Version: 2.1
Name: fiberphotopy
Version: 0.2.31
Summary: Package for loading and processing fiber photometry data
Home-page: https://github.com/kpuhger/fiberphotopy
License: MIT
Author: kpuhger
Author-email: krpuhger@gmail.com
Requires-Python: >=3.10,<3.12
Classifier: License :: OSI Approved :: MIT License
Classifier: Programming Language :: Python :: 3
Classifier: Programming Language :: Python :: 3.10
Requires-Dist: PyYAML (>=6.0,<7.0)
Requires-Dist: matplotlib (>=3.5,<4.0)
Requires-Dist: numpy (>=1.23,<2.0)
Requires-Dist: openpyxl (>=3.0.10,<4.0.0)
Requires-Dist: pandas (>=1.5,<2.0)
Requires-Dist: pingouin (>=0.5.2,<0.6.0)
Requires-Dist: ruamel.yaml (>=0.17.21,<0.18.0)
Requires-Dist: scipy (>=1.9,<2.0)
Requires-Dist: seaborn (>=0.12,<0.13)
Project-URL: Repository, https://github.com/kpuhger/fiberphotopy
